{
  "presets": {
    "low": {
      "modules": {
        "networking.packet_rate": "high",
        "networking.packet_buffer": "standard",
        "networking.packet_size": "standard",
        "networking.upload": "default",
        "models": "low",
        "world": "off",
        "shaders": "low",
        "textures": "low",
        "shadows": "off",
        "effects": "low",
        "water": "low",
        "post_processing": "low",
        "pyrovision": "low",
        "motion_blur": "off",
        "antialiasing": "off",
        "texture_filter": "bilinear",
        "characters": "low",
        "decals": "off",
        "sprays": "off",
        "gibs": "off",
        "ragdolls": "off",
        "hud.outlines": "off",
        "sound": "low"
      }
    },
    "medium": {
      "modules": {
        "networking.packet_rate": "high",
        "networking.packet_buffer": "standard",
        "networking.packet_size": "standard",
        "networking.upload": "default",
        "models": "medium",
        "world": "medium",
        "shaders": "medium",
        "textures": "medium",
        "shadows": "medium",
        "effects": "medium",
        "water": "medium",
        "post_processing": "medium",
        "pyrovision": "medium",
        "motion_blur": "off",
        "antialiasing": "fxaa_low",
        "texture_filter": "trilinear",
        "characters": "medium",
        "decals": "medium",
        "sprays": "off",
        "gibs": "off",
        "ragdolls": "off",
        "hud.outlines": "medium",
        "sound": "medium"
      }
    },
    "high": {
      "modules": {
        "networking.packet_rate": "high",
        "networking.packet_buffer": "standard",
        "networking.packet_size": "standard",
        "networking.upload": "default",
        "models": "high",
        "world": "high",
        "shaders": "high",
        "textures": "high",
        "shadows": "high",
        "effects": "high",
        "water": "high",
        "post_processing": "high",
        "pyrovision": "high",
        "motion_blur": "high",
        "antialiasing": "msaa_4x",
        "texture_filter": "aniso_4x",
        "characters": "high",
        "decals": "high",
        "sprays": "on",
        "gibs": "high",
        "ragdolls": "on",
        "hud.outlines": "high",
        "sound": "high"
      }
    },
    "ultra": {
      "modules": {
        "networking.packet_rate": "high",
        "networking.packet_buffer": "standard",
        "networking.packet_size": "standard",
        "networking.upload": "default",
        "models": "ultra",
        "world": "ultra",
        "shaders": "ultra",
        "textures": "ultra",
        "shadows": "ultra",
        "effects": "high",
        "water": "ultra",
        "post_processing": "ultra",
        "pyrovision": "ultra",
        "motion_blur": "ultra",
        "antialiasing": "msaa_16x",
        "texture_filter": "bilinear",
        "characters": "ultra",
        "decals": "ultra",
        "sprays": "on",
        "gibs": "ultra",
        "ragdolls": "on",
        "hud.outlines": "high",
        "sound": "ultra"
      }
    }
  }
}
